data_analysis_helper/__about__.py
data_analysis_helper/__init__.py
data_analysis_helper/expr.py
data_analysis_helper/plot.py
data_analysis_helper/root.py
data_analysis_helper/stats.py
data_analysis_helper-0.13.0.dist-info/METADATA
data_analysis_helper-0.13.0.dist-info/WHEEL
data_analysis_helper-0.13.0.dist-info/licenses/LICENSE.txt
data_analysis_helper-0.13.0.dist-info/RECORD
