Metadata-Version: 2.4
Name: data-analysis-helper
Version: 0.13.0
Project-URL: Documentation, https://github.com/laf070810/data-analysis-helper#readme
Project-URL: Issues, https://github.com/laf070810/data-analysis-helper/issues
Project-URL: Source, https://github.com/laf070810/data-analysis-helper
Author-email: Anfeng Li <anfeng.li@cern.ch>
License-Expression: MIT
License-File: LICENSE.txt
Classifier: Development Status :: 4 - Beta
Classifier: Programming Language :: Python
Classifier: Programming Language :: Python :: 3.8
Classifier: Programming Language :: Python :: 3.9
Classifier: Programming Language :: Python :: 3.10
Classifier: Programming Language :: Python :: 3.11
Classifier: Programming Language :: Python :: 3.12
Classifier: Programming Language :: Python :: Implementation :: CPython
Classifier: Programming Language :: Python :: Implementation :: PyPy
Requires-Python: >=3.8
